easy_ecs_sim/__init__.py
easy_ecs_sim/component.py
easy_ecs_sim/context.py
easy_ecs_sim/context_service.py
easy_ecs_sim/ecs_service.py
easy_ecs_sim/signature.py
easy_ecs_sim/storage/__init__.py
easy_ecs_sim/storage/database.py
easy_ecs_sim/storage/demography.py
easy_ecs_sim/storage/id_generator.py
easy_ecs_sim/storage/index.py
easy_ecs_sim/storage/my_database.py
easy_ecs_sim/system.py
easy_ecs_sim/systems.py
easy_ecs_sim/timebox_manager.py
easy_ecs_sim/utils.py
easy_ecs_sim-0.1.26.dist-info/LICENSE
easy_ecs_sim-0.1.26.dist-info/METADATA
easy_ecs_sim-0.1.26.dist-info/WHEEL
easy_ecs_sim-0.1.26.dist-info/RECORD
