Metadata-Version: 2.1
Name: easy-ecs-sim
Version: 0.1.26
Summary: Entity Component System
Home-page: https://github.com/flegac/easy-ecs
License: MIT
Author: flegac
Author-email: florent.legac@gmail.com
Requires-Python: >=3.12,<4.0
Classifier: License :: OSI Approved :: MIT License
Classifier: Operating System :: OS Independent
Classifier: Programming Language :: Python :: 3
Classifier: Programming Language :: Python :: 3.12
Classifier: Programming Language :: Python :: 3.13
Requires-Dist: easy-kit
Requires-Dist: pydantic
Project-URL: Repository, https://github.com/flegac/easy-ecs
